__init__.py
build.py
docker.py
util.py
zdocker-1.0.23.dist-info/METADATA
zdocker-1.0.23.dist-info/WHEEL
zdocker-1.0.23.dist-info/entry_points.txt
zdocker-1.0.23.dist-info/top_level.txt
zdocker-1.0.23.dist-info/RECORD
