Metadata-Version: 2.4
Name: zdocker
Version: 1.0.23
Summary: It is the build system of linux, which is based on Conan
Author-email: "Zhiguo.Zhu" <294966@qq.com>
Requires-Python: <=3.14,>=3.8
Requires-Dist: dockerpty==0.4.1
Requires-Dist: docker==7.1.0
Requires-Dist: psutil==6.1.0
Requires-Dist: dohq-artifactory==0.10.1
